moonstreamdb/__init__.py
moonstreamdb/blockchain.py
moonstreamdb/cli.py
moonstreamdb/db.py
moonstreamdb/models.py
moonstreamdb/networks.py
moonstreamdb/subscriptions.py
moonstreamdb/version.py
moonstreamdb-0.4.6.dist-info/METADATA
moonstreamdb-0.4.6.dist-info/WHEEL
moonstreamdb-0.4.6.dist-info/entry_points.txt
moonstreamdb-0.4.6.dist-info/top_level.txt
moonstreamdb-0.4.6.dist-info/RECORD
