Metadata-Version: 2.1
Name: moonstreamdb
Version: 0.4.6
Summary: Moonstream database
Home-page: https://github.com/bugout-dev/moonstream
Author: Bugout.dev
Author-email: engineers@bugout.dev
License: Apache License 2.0
Platform: all
Classifier: Development Status :: 2 - Pre-Alpha
Classifier: Intended Audience :: Developers
Classifier: Natural Language :: English
Classifier: Programming Language :: Python
Classifier: Programming Language :: Python :: 3
Classifier: Programming Language :: Python :: 3.8
Classifier: Programming Language :: Python :: Implementation :: CPython
Classifier: Topic :: Software Development :: Libraries
Classifier: Topic :: Software Development :: Libraries :: Python Modules
Requires-Python: >=3.6
Requires-Dist: alembic
Requires-Dist: psycopg2-binary
Requires-Dist: sqlalchemy >=2.0.4
Provides-Extra: dev
Requires-Dist: black ; extra == 'dev'
Requires-Dist: isort ; extra == 'dev'
Requires-Dist: mypy ; extra == 'dev'
Provides-Extra: distribute
Requires-Dist: build ; extra == 'distribute'
Requires-Dist: twine ; extra == 'distribute'
